nxstools/__init__.py
nxstools/filenamegenerator.py
nxstools/filewriter.py
nxstools/h5cppwriter.py
nxstools/h5pywriter.py
nxstools/h5rediswriter.py
nxstools/nxsargparser.py
nxstools/nxscollect.py
nxstools/nxsconfig.py
nxstools/nxscreate.py
nxstools/nxscreator.py
nxstools/nxsdata.py
nxstools/nxsdevicetools.py
nxstools/nxsetup.py
nxstools/nxsfileinfo.py
nxstools/nxsfileparser.py
nxstools/nxsparser.py
nxstools/nxsxml.py
nxstools/redisutils.py
nxstools/release.py
nxstools/ontology/__init__.py
nxstools/ontology/ontology.json
nxstools/pyeval/__init__.py
nxstools/pyeval/absorber.py
nxstools/pyeval/beamtimeid.py
nxstools/pyeval/cobold.py
nxstools/pyeval/common.py
nxstools/pyeval/dalsa.py
nxstools/pyeval/dalsavds.py
nxstools/pyeval/datasignal.py
nxstools/pyeval/dcm.py
nxstools/pyeval/eigerdectris.py
nxstools/pyeval/lambdavds.py
nxstools/pyeval/limaccd.py
nxstools/pyeval/lmbd.py
nxstools/pyeval/marccd.py
nxstools/pyeval/minipix.py
nxstools/pyeval/mssar.py
nxstools/pyeval/mythen.py
nxstools/pyeval/pco.py
nxstools/pyeval/pe.py
nxstools/pyeval/pilatus.py
nxstools/pyeval/pilc.py
nxstools/pyeval/pilcvds.py
nxstools/pyeval/qbpm.py
nxstools/pyeval/scdataset.py
nxstools/pyeval/secop.py
nxstools/pyeval/tangovimba.py
nxstools/pyeval/timestamp.py
nxstools/pyeval/xspress3.py
nxstools/xmltemplates/__init__.py
nxstools/xmltemplates/absorber.xml
nxstools/xmltemplates/absorber_foil.ds.xml
nxstools/xmltemplates/absorber_thickness.ds.xml
nxstools/xmltemplates/beamstop.xml
nxstools/xmltemplates/beamtime_filename.ds.xml
nxstools/xmltemplates/beamtime_id.ds.xml
nxstools/xmltemplates/beamtimefname.ds.xml
nxstools/xmltemplates/beamtimefname.xml
nxstools/xmltemplates/beamtimeid.ds.xml
nxstools/xmltemplates/beamtimeid.xml
nxstools/xmltemplates/chcut.xml
nxstools/xmltemplates/chcut_crystal.ds.xml
nxstools/xmltemplates/chcut_unitcalibration.ds.xml
nxstools/xmltemplates/chemical_formula.ds.xml
nxstools/xmltemplates/client_start_time.ds.xml
nxstools/xmltemplates/cobold.xml
nxstools-4.36.0.dist-info/METADATA
nxstools-4.36.0.dist-info/WHEEL
nxstools-4.36.0.dist-info/top_level.txt
nxstools-4.36.0.dist-info/RECORD
