Metadata-Version: 2.1
Name: nxstools
Version: 4.36.0
Summary: Configuration tools for NeXDaTaS Tango Servers
Home-page: http://github.com/nexdatas/nxstools
Author: Jan Kotanski, Eugen Wintersberger , Halil Pasic
Author-email: jankotan@gmail.com, eugen.wintersberger@gmail.com, halil.pasic@gmail.com
Maintainer: Jan Kotanski, Eugen Wintersberger , Halil Pasic
Maintainer-email: jankotan@gmail.com, eugen.wintersberger@gmail.com, halil.pasic@gmail.com
License: GNU GENERAL PUBLIC LICENSE version 3
Keywords: configuration writer Tango component nexus data
Platform: Linux
Classifier: Development Status :: 5 - Production/Stable
Classifier: Intended Audience :: Science/Research
Classifier: Topic :: Scientific/Engineering :: Physics
Classifier: Topic :: Software Development :: Libraries :: Python Modules
Classifier: License :: OSI Approved :: GNU General Public License v3 (GPLv3)
Classifier: Programming Language :: Python :: 3
Classifier: Programming Language :: Python :: 3.5
Classifier: Programming Language :: Python :: 3.6
Classifier: Programming Language :: Python :: 3.7
Classifier: Programming Language :: Python :: 3.8
Classifier: Programming Language :: Python :: 3.9
Classifier: Programming Language :: Python :: 3.10
Classifier: Programming Language :: Python :: 3.11
Classifier: Programming Language :: Python :: 3.12
Classifier: Programming Language :: Python :: 3.13
Requires-Dist: argcomplete
Requires-Dist: lxml
Requires-Dist: numpy (>1.6.0)
Requires-Dist: pytz
Requires-Dist: pyyaml
